consul_sdk/__init__.py
consul_sdk/client.py
consul_sdk/consul_lock.py
consul_sdk/test_consul_client.py
consul_sdk/test_consul_lock.py
consul_sdk/test_consul_lock_integration.py
consul_sdk/test_util.py
consul_sdk/util.py
consul_sdk-0.0.12.dist-info/METADATA
consul_sdk-0.0.12.dist-info/WHEEL
consul_sdk-0.0.12.dist-info/top_level.txt
consul_sdk-0.0.12.dist-info/RECORD
